{
    "asset_gid": "148/753974",
    "geometry": {
        "0-level-0": "73/375465",
        "0-level-1": "120/612985",
        "0-level-2": "155/788929",
        "0-level-3": "52/270932",
        "0-level-4": "148/753873",
        "1-level-0": "146/744514",
        "1-level-1": "127/648567",
        "1-level-2": "149/756599",
        "1-level-3": "28/152701",
        "1-level-4": "155/785604",
        "2-level-0": "5/36782",
        "2-level-1": "112/571967",
        "2-level-2": "74/383440",
        "2-level-3": "138/702529",
        "2-level-4": "148/753873"
    },
    "texture": {
        "0-level-0": "26/141836",
        "0-level-1": "65/337948",
        "0-level-2": "143/725518",
        "0-level-3": "33/177502",
        "0-level-4": "148/753873",
        "1-level-0": "40/210730",
        "1-level-1": "127/648567",
        "1-level-2": "67/346780",
        "1-level-3": "54/281874",
        "1-level-4": "121/619492",
        "2-level-0": "17/96096",
        "2-level-1": "127/648567",
        "2-level-2": "52/270315",
        "2-level-3": "134/681169",
        "2-level-4": "90/462389"
    },
    "material": {
        "0-level-0": "17/96096",
        "0-level-1": "35/185834",
        "0-level-2": "113/575306",
        "0-level-3": "109/558840",
        "0-level-4": "48/253978",
        "1-level-0": "143/728849",
        "1-level-1": "15/86204",
        "1-level-2": "81/416007",
        "1-level-3": "28/151558",
        "1-level-4": "53/277962",
        "2-level-0": "144/731018",
        "2-level-1": "98/500032",
        "2-level-2": "99/506821",
        "2-level-3": "152/773342",
        "2-level-4": "53/277962"
    },
    "plausibility": {
        "0-level-0": "92/471364",
        "0-level-1": "73/376655",
        "0-level-2": "149/759369",
        "0-level-3": "54/280139",
        "0-level-4": "48/253978",
        "1-level-0": "92/471364",
        "1-level-1": "86/442157",
        "1-level-2": "155/788929",
        "1-level-3": "117/596411",
        "1-level-4": "148/753873",
        "2-level-0": "40/211379",
        "2-level-1": "111/567762",
        "2-level-2": "54/282763",
        "2-level-3": "23/126322",
        "2-level-4": "48/252997"
    },
    "artifacts": {
        "0-level-0": "17/96096",
        "0-level-1": "1/15189",
        "0-level-2": "5/36782",
        "0-level-3": "77/396692",
        "0-level-4": "155/788929",
        "1-level-0": "40/211379",
        "1-level-1": "155/785604",
        "1-level-2": "134/681169",
        "1-level-3": "52/270932",
        "1-level-4": "6/43034",
        "2-level-0": "143/728849",
        "2-level-1": "1/15189",
        "2-level-2": "152/773867",
        "2-level-3": "28/152701",
        "2-level-4": "8/50863"
    },
    "preference": {
        "0-level-0": "103/527548",
        "0-level-1": "67/346780",
        "0-level-2": "155/788929",
        "0-level-3": "74/383440",
        "0-level-4": "48/252997",
        "1-level-0": "146/744514",
        "1-level-1": "131/667744",
        "1-level-2": "45/238720",
        "1-level-3": "54/282763",
        "1-level-4": "48/253978",
        "2-level-0": "63/327660",
        "2-level-1": "97/499599",
        "2-level-2": "105/538820",
        "2-level-3": "54/282763",
        "2-level-4": "149/756599"
    }
}